{"components_basic_configprovider.md":"T7rOvpAy","components_basic_button.md":"ULPGKWIJ","components_basic_transition.md":"5EM22aOE","components_basic_icon.md":"VGR7LEJV","components_bingo_hiteggs.md":"mR_wqDFH","components_bingo_marquee.md":"ipvARLix","components_bingo_giftbox.md":"7EIdom92","components_basic_popup.md":"wXCAYGdN","components_basic_overlay.md":"kP43nfg_","components_bingo_turntable.md":"3cpf2dd_","components_bingo_dollmachine.md":"CYA-9vXA","components_bingo_shakedice.md":"F-ofaXb4","components_basic_cell.md":"3qTqY9zN","components_business_barrage.md":"sSVqiKbL","components_business_addresslist.md":"-LGvtfxf","components_business_category.md":"nSjDnVnN","components_business_ecard.md":"ppzL2cWC","components_business_card.md":"-zdu12z2","components_business_signature.md":"dINdU8JL","components_business_comment.md":"oELBjO1E","components_business_invoice.md":"J8_sF5fc","components_business_address.md":"nbOgUxU6","components_business_timeselect.md":"njrVtb2c","components_business_sku.md":"4v18RKSl","components_dentry_codeinput.md":"Xqwjqf5g","components_dentry_checkbox.md":"Zlikrzde","components_dentry_cascader.md":"J3GPBnNz","components_dentry_inputnumber.md":"AE0v7pw3","components_dentry_datepicker.md":"_NuVMYe1","components_dentry_input.md":"sOgJWdzh","components_dentry_form.md":"FxwXoSO0","components_dentry_calendar.md":"6vn7-mL2","components_dentry_numberkeyboard.md":"K8B3-CVN","components_dentry_radio.md":"QMCSTbNn","components_dentry_textarea.md":"D4H7F2Hu","components_dentry_rate.md":"Avv3KSKd","components_dentry_shortpassword.md":"3kcHspWH","components_dentry_picker.md":"lIXxncwC","components_dentry_searchbar.md":"ujZyVc9U","components_dentry_range.md":"LXw-Gylv","components_exhibition_animate.md":"XVN3H9Rp","components_exhibition_avatar.md":"UmbLiOM5","components_dentry_uploader.md":"uonQ2RvJ","components_exhibition_circleprogress.md":"KteIAYN0","components_exhibition_badge.md":"mEVus7A7","components_exhibition_collapse.md":"QYsyw2tQ","components_exhibition_ellipsis.md":"X07yHWnQ","components_exhibition_countup.md":"MkYv1IA6","components_exhibition_empty.md":"U7eTzjTx","components_exhibition_list.md":"xmxmBc1g","components_exhibition_countdown.md":"UDP-RrKk","components_exhibition_loadingpage.md":"ffmWsRww","components_exhibition_imagepreview.md":"GdkSYvI1","components_exhibition_noticebar.md":"aI0_yN_A","components_exhibition_price.md":"Z3Xg4I7_","components_exhibition_skeleton.md":"jd_TSrs0","components_exhibition_progress.md":"s5k1eUSx","components_exhibition_steps.md":"bsaYZgi6","components_exhibition_popover.md":"7ujm9_BN","components_exhibition_tag.md":"UmFVntfT","components_exhibition_swiper.md":"LM3e0Yt-","components_exhibition_table.md":"210URiJ_","components_exhibition_trendarrow.md":"e76tih0v","components_exhibition_watermark.md":"ArLjH01h","components_exhibition_tour.md":"vh8Ctw-o","components_feedback_drag.md":"KvOgcnxc","components_feedback_backtop.md":"y_Kx89FW","components_feedback_actionsheet.md":"FIOpF6nd","components_feedback_dialog.md":"Gw5BplEJ","components_feedback_swipe.md":"k-qIZsGU","components_feedback_notify.md":"VRZrOmCm","components_layout_divider.md":"raCLl0Y_","components_feedback_switch.md":"vwnlWJ8k","components_feedback_toast.md":"E0RKu-ng","components_layout_grid.md":"kLKU3tR8","components_layout_sticky.md":"TXmOa2MS","components_layout_safearea.md":"A_DqqN2G","components_layout_layout.md":"HboeRjZ5","components_nav_indicator.md":"iVJpLsgt","components_nav_fixednav.md":"Uxua3Clf","components_nav_navbar.md":"jYKKp6UB","components_nav_elevator.md":"RgTZsK8g","components_nav_pagination.md":"Nlhuw-M_","components_nav_sidenavbar.md":"fNKyXv4r","components_nav_menu.md":"6bpEQFsf","components_template.md":"hnQAhCTb","guide_overview.md":"Q_sVaehk","guide_i18n.md":"u6YqIKCQ","guide_changelog.md":"wlpsarVa","guide_faq.md":"KeFAPT7u","index.md":"ceX1PLw3","guide_theme.md":"zvjB0M5q","components_nav_tabbar.md":"Oz_Dk9F-","guide_quick-start.md":"uNbL5lte","components_nav_tabs.md":"A8SZJEqw"}
